<Products><data><image>https://cdn.hamrobazaar.com/2285207_0821afb89d67e115_small.jpg</image><title>Tv/ Computer Rack</title><link>https://hamrobazaar.com/i2285207-tv-computer-rack.html</link><detail>Tv/ Computer Rack  Tv Rack With Space For Cd Player And Speaker Length 24  Inch Breadth  18.5 Height 30.5  Inch Serious Buyer , Please Call...Seller: Shyam ji.   - Baphal, Kathmandu</detail><seller>Shyam ji.</seller><seller_items>https://hamrobazaar.com/useritems.php?user_siteid=2285207</seller_items><date>21-08-2020</date><price>Rs. 1,999(Used)</price></data><data><image>https://cdn.hamrobazaar.com/2284714_082048ghf7g14h8e_small.jpg</image><title>Computer Table</title><link>https://hamrobazaar.com/i2284714-computer-table.html</link><detail>Computer Table  Computer Table Plus Study Table Has Wheels Perfect Condition Delivery Not Available, Only Pickup...Seller: Matina KC   - Talchhikhel, Lalitpur</detail><seller>Matina KC</seller><seller_items>https://hamrobazaar.com/useritems.php?user_siteid=2284714</seller_items><date>20-08-2020</date><price>Rs. 2,000(Like New)</price></data><data><image>https://cdn.hamrobazaar.com/2282875_0818fch7f45d54g5_small.jpg</image><title>Computer Table, Double Computer And Office Table</title><link>https://hamrobazaar.com/i2282875-computer-table-double-computer-and-office-table.html</link><detail>Computer Table, Double Computer And Office Table  Computer Table For Study Home And Office, Office Table, Computer Table, Study Table Size: Length: 4 Feet Width: 1 Feet 4...Seller: Pappu Shah   - Chardobato, Bhaktapur</detail><seller>Pappu Shah</seller><seller_items>https://hamrobazaar.com/useritems.php?user_siteid=2282875</seller_items><date>18-08-2020</date><price>Rs. 5,000(Like New)</price></data><data><image>https://cdn.hamrobazaar.com/2288368_08245818818fhd5h_small.jpg</image><title>Furniture For Computer Set</title><link>https://hamrobazaar.com/i2288368-furniture-for-computer-set.html</link><detail>Furniture For Computer Set  Size: 47"x23"x60" Lxbxh This Furniture Is Very Useful To Put Your Computer. Printer And Office Documents ...Seller: Sabin Bajracharya   - Bagbazar, Kathmandu</detail><seller>Sabin Bajracharya</seller><seller_items>https://hamrobazaar.com/useritems.php?user_siteid=2288368</seller_items><date>24-08-2020</date><price>Rs. 10,000(Used)</price></data><data><image>https://cdn.hamrobazaar.com/2286019_0822hfaa94g5f22b_small.jpg</image><title>5 Set Of Pc Computer On Sell</title><link>https://hamrobazaar.com/i2286019-5-set-of-pc-computer-on-sell.html</link><detail>5 Set Of Pc Computer On Sell Processor: Intel Pentium 4 or lower &#160;|&#160; Ram (GB): 2 &#160;|&#160; HDD (GB/TB): 250 &#160;|&#160; Screen Type: LCD &#160;|&#160; Screen Size (inch): 15 Institute Ko Lagee Kenaa Ko So Kam Na Bhayraa Bechnaa Lakoo Any One Intrested Then U Can Contact 14000 Per Set With All ...Seller: Ashwin kc   - Belwas, Butwal</detail><seller>Ashwin kc</seller><seller_items>https://hamrobazaar.com/useritems.php?user_siteid=2286019</seller_items><date>22-08-2020</date><price>Rs. 14,000(Like New)</price></data></Products>